processing/__init__.py
processing/utils.py
processing/video_capture.py
image_by_picture-0.0.1.dist-info/METADATA
image_by_picture-0.0.1.dist-info/WHEEL
image_by_picture-0.0.1.dist-info/top_level.txt
image_by_picture-0.0.1.dist-info/RECORD
