Metadata-Version: 2.1
Name: image-by-picture
Version: 0.0.1
Summary: Image Processing by Picture using OpenCV and Numpy
Home-page: https://github.com/NEQUITA/image_by_picture
Author: Nequita
License: UNKNOWN
Platform: UNKNOWN
Requires-Python: >=3.8
Requires-Dist: opencv-python
Requires-Dist: imutils
